odoo8_addon_l10n_fr_ubl-8.0.1.0.0.99.dev2-py2.7-nspkg.pth
odoo8_addon_l10n_fr_ubl-8.0.1.0.0.99.dev2.dist-info/DESCRIPTION.rst
odoo8_addon_l10n_fr_ubl-8.0.1.0.0.99.dev2.dist-info/METADATA
odoo8_addon_l10n_fr_ubl-8.0.1.0.0.99.dev2.dist-info/RECORD
odoo8_addon_l10n_fr_ubl-8.0.1.0.0.99.dev2.dist-info/WHEEL
odoo8_addon_l10n_fr_ubl-8.0.1.0.0.99.dev2.dist-info/metadata.json
odoo8_addon_l10n_fr_ubl-8.0.1.0.0.99.dev2.dist-info/namespace_packages.txt
odoo8_addon_l10n_fr_ubl-8.0.1.0.0.99.dev2.dist-info/top_level.txt
odoo_addons/l10n_fr_ubl/README.rst
odoo_addons/l10n_fr_ubl/__init__.py
odoo_addons/l10n_fr_ubl/__openerp__.py
odoo_addons/l10n_fr_ubl/i18n/l10n_fr_ubl.pot
odoo_addons/l10n_fr_ubl/models/__init__.py
odoo_addons/l10n_fr_ubl/models/base_ubl.py
